[
	{
		"constant": false,
		"inputs": [],
		"name": "withdrawInterest",
		"outputs": [],
		"payable": false,
		"stateMutability": "nonpayable",
		"type": "function"
	},
	{
		"constant": false,
		"inputs": [
			{
				"name": "_amount",
				"type": "uint256"
			}
		],
		"name": "withdrawStakeAndInterest",
		"outputs": [],
		"payable": false,
		"stateMutability": "nonpayable",
		"type": "function"
	},
	{
		"constant": false,
		"inputs": [],
		"name": "updateGlobalYield",
		"outputs": [],
		"payable": false,
		"stateMutability": "nonpayable",
		"type": "function"
	},
	{
		"constant": true,
		"inputs": [],
		"name": "interestData",
		"outputs": [
			{
				"name": "globalTotalStaked",
				"type": "uint256"
			},
			{
				"name": "globalYieldPerToken",
				"type": "uint256"
			},
			{
				"name": "lastUpdated",
				"type": "uint256"
			}
		],
		"payable": false,
		"stateMutability": "view",
		"type": "function"
	},
	{
		"constant": true,
		"inputs": [],
		"name": "vaultAddress",
		"outputs": [
			{
				"name": "",
				"type": "address"
			}
		],
		"payable": false,
		"stateMutability": "view",
		"type": "function"
	},
	{
		"constant": true,
		"inputs": [],
		"name": "stakingStartTime",
		"outputs": [
			{
				"name": "",
				"type": "uint256"
			}
		],
		"payable": false,
		"stateMutability": "view",
		"type": "function"
	},
	{
		"constant": true,
		"inputs": [],
		"name": "totalReward",
		"outputs": [
			{
				"name": "",
				"type": "uint256"
			}
		],
		"payable": false,
		"stateMutability": "view",
		"type": "function"
	},
	{
		"constant": true,
		"inputs": [
			{
				"name": "_staker",
				"type": "address"
			}
		],
		"name": "getYieldData",
		"outputs": [
			{
				"name": "",
				"type": "uint256"
			},
			{
				"name": "",
				"type": "uint256"
			}
		],
		"payable": false,
		"stateMutability": "view",
		"type": "function"
	},
	{
		"constant": false,
		"inputs": [
			{
				"name": "_amount",
				"type": "uint256"
			}
		],
		"name": "stake",
		"outputs": [],
		"payable": false,
		"stateMutability": "nonpayable",
		"type": "function"
	},
	{
		"constant": true,
		"inputs": [],
		"name": "stakingPeriod",
		"outputs": [
			{
				"name": "",
				"type": "uint256"
			}
		],
		"payable": false,
		"stateMutability": "view",
		"type": "function"
	},
	{
		"constant": true,
		"inputs": [
			{
				"name": "_staker",
				"type": "address"
			}
		],
		"name": "getStakerData",
		"outputs": [
			{
				"name": "",
				"type": "uint256"
			},
			{
				"name": "",
				"type": "uint256"
			}
		],
		"payable": false,
		"stateMutability": "view",
		"type": "function"
	},
	{
		"constant": true,
		"inputs": [
			{
				"name": "_staker",
				"type": "address"
			}
		],
		"name": "calculateInterest",
		"outputs": [
			{
				"name": "",
				"type": "uint256"
			}
		],
		"payable": false,
		"stateMutability": "view",
		"type": "function"
	},
	{
		"constant": true,
		"inputs": [
			{
				"name": "_staker",
				"type": "address"
			}
		],
		"name": "getStatsData",
		"outputs": [
			{
				"name": "",
				"type": "uint256"
			},
			{
				"name": "",
				"type": "uint256"
			},
			{
				"name": "",
				"type": "uint256"
			},
			{
				"name": "",
				"type": "uint256"
			},
			{
				"name": "",
				"type": "uint256"
			}
		],
		"payable": false,
		"stateMutability": "view",
		"type": "function"
	},
	{
		"inputs": [
			{
				"name": "_stakeToken",
				"type": "address"
			},
			{
				"name": "_rewardToken",
				"type": "address"
			},
			{
				"name": "_stakingPeriod",
				"type": "uint256"
			},
			{
				"name": "_totalRewardToBeDistributed",
				"type": "uint256"
			},
			{
				"name": "_vaultAdd",
				"type": "address"
			}
		],
		"payable": false,
		"stateMutability": "nonpayable",
		"type": "constructor"
	},
	{
		"anonymous": false,
		"inputs": [
			{
				"indexed": true,
				"name": "staker",
				"type": "address"
			},
			{
				"indexed": false,
				"name": "value",
				"type": "uint256"
			},
			{
				"indexed": false,
				"name": "_globalYieldPerToken",
				"type": "uint256"
			}
		],
		"name": "Staked",
		"type": "event"
	},
	{
		"anonymous": false,
		"inputs": [
			{
				"indexed": true,
				"name": "staker",
				"type": "address"
			},
			{
				"indexed": false,
				"name": "value",
				"type": "uint256"
			},
			{
				"indexed": false,
				"name": "_globalYieldPerToken",
				"type": "uint256"
			}
		],
		"name": "StakeWithdrawn",
		"type": "event"
	},
	{
		"anonymous": false,
		"inputs": [
			{
				"indexed": true,
				"name": "staker",
				"type": "address"
			},
			{
				"indexed": false,
				"name": "_value",
				"type": "uint256"
			},
			{
				"indexed": false,
				"name": "_globalYieldPerToken",
				"type": "uint256"
			}
		],
		"name": "InterestCollected",
		"type": "event"
	}
]